noop.cpython-311-darwin.so
sqlite_ulid/__init__.py
sqlite_ulid/ulid0.dylib
sqlite_ulid/version.py
sqlite_ulid-0.2.1.dist-info/METADATA
sqlite_ulid-0.2.1.dist-info/WHEEL
sqlite_ulid-0.2.1.dist-info/top_level.txt
sqlite_ulid-0.2.1.dist-info/RECORD
