Metadata-Version: 2.1
Name: sqlite-ulid
Version: 0.2.1
Home-page: https://github.com/asg017/sqlite-ulid
Author: Alex Garcia
License: MIT License, Apache License, Version 2.0
Project-URL: Issues, https://github.com/asg017/sqlite-ulid/issues
Project-URL: CI, https://github.com/asg017/sqlite-ulid/actions
Project-URL: Changelog, https://github.com/asg017/sqlite-ulid/releases
Requires-Python: >=3.6
Provides-Extra: test
Requires-Dist: pytest ; extra == 'test'
